auto_compiler/__init__.py
auto_compiler/auto_compiler.py
auto_compiler/compiler.py
auto_compiler/errors.py
auto_compiler/source.py
auto_compiler/compilers/DotnetCompiler.py
auto_compiler/compilers/GppCompiler.py
auto_compiler/compilers/IdentityCompiler.py
auto_compiler/compilers/JavaCompiler.py
auto_compiler/compilers/RustCompiler.py
auto_compiler/compilers/__init__.py
auto_compiler-0.2.1.dist-info/LICENCE
auto_compiler-0.2.1.dist-info/METADATA
auto_compiler-0.2.1.dist-info/WHEEL
auto_compiler-0.2.1.dist-info/top_level.txt
auto_compiler-0.2.1.dist-info/RECORD
