Metadata-Version: 2.2
Name: auto-compiler
Version: 0.2.1
Summary: A system for auto compiling files
Author-email: INSALGO <insalgo.contact@gmail.com>
Project-URL: Homepage, https://github.com/INSAlgo/auto_compiler
Requires-Python: >=3.10
License-File: LICENCE
